ansys/materials/manager/__init__.py
ansys/materials/manager/_models/__init__.py
ansys/materials/manager/_models/_common/__init__.py
ansys/materials/manager/_models/_common/_base.py
ansys/materials/manager/_models/_common/_exceptions.py
ansys/materials/manager/_models/_common/_packages.py
ansys/materials/manager/_models/_common/constant.py
ansys/materials/manager/_models/_common/piecewise_linear.py
ansys/materials/manager/_models/_common/polynomial.py
ansys/materials/manager/_models/_fluent/__init__.py
ansys/materials/manager/_models/_fluent/ideal_gas.py
ansys/materials/manager/_models/_fluent/simple_properties.py
ansys/materials/manager/_models/_mapdl/__init__.py
ansys/materials/manager/_models/_mapdl/anisotropic_elasticity.py
ansys/materials/manager/_models/_mapdl/simple_properties.py
ansys/materials/manager/_models/py.typed
ansys/materials/manager/material.py
ansys/materials/manager/material_manager.py
ansys/materials/manager/serialize.py
ansys/materials/manager/util/__init__.py
ansys/materials/manager/util/common.py
ansys/materials/manager/util/mapdl/__init__.py
ansys/materials/manager/util/mapdl/mapdl_reader.py
ansys/materials/manager/util/mapdl/mpdata_parser.py
ansys/materials/manager/util/mapdl/tbdata_parser.py
ansys/materials/manager/util/matml/__init__.py
ansys/materials/manager/util/matml/matml_from_material.py
ansys/materials/manager/util/matml/matml_parser.py
ansys/materials/manager/util/matml/matml_property_map.py
ansys/materials/manager/util/matml/matml_to_material.py
ansys_materials_manager-0.3.1.dist-info/METADATA
ansys_materials_manager-0.3.1.dist-info/WHEEL
ansys_materials_manager-0.3.1.dist-info/licenses/AUTHORS
ansys_materials_manager-0.3.1.dist-info/licenses/LICENSE
ansys_materials_manager-0.3.1.dist-info/RECORD
