Metadata-Version: 2.4
Name: ansys-materials-manager
Version: 0.3.1
Summary: Python package to unify material management across the ansys portfolio
License: MIT
License-File: AUTHORS
License-File: LICENSE
Author: ANSYS, Inc.
Author-email: ansys.support@ansys.com
Maintainer: PyAnsys developers
Maintainer-email: pyansys.core@ansys.com
Requires-Python: >=3.10,<3.14
Classifier: Development Status :: 4 - Beta
Classifier: License :: OSI Approved :: MIT License
Classifier: Operating System :: OS Independent
Classifier: Programming Language :: Python :: 3
Classifier: Programming Language :: Python :: 3.10
Classifier: Programming Language :: Python :: 3.11
Classifier: Programming Language :: Python :: 3.12
Classifier: Programming Language :: Python :: 3.13
Requires-Dist: numpy (>=1.24,<3)
Project-URL: Documentation, https://manager.materials.docs.pyansys.com
Project-URL: Repository, https://github.com/ansys/pymaterials-manager
